pysocmed/__init__.py
pysocmed/api.py
pysocmed-0.2.1.dist-info/LICENSE
pysocmed-0.2.1.dist-info/METADATA
pysocmed-0.2.1.dist-info/WHEEL
pysocmed-0.2.1.dist-info/top_level.txt
pysocmed-0.2.1.dist-info/RECORD
